{"legend":{"id4":"1-2","id7":"3","id4_desc":"geringe bis mittlere Belastung","id1":"0","id6_desc":"mittlere bis hohe Belastung","id5":"2","id3":"1","id6":"2-3","id3_desc":"geringe Belastung","id2":"0-1","id1_desc":"keine Belastung","id7_desc":"hohe Belastung","id2_desc":"keine bis geringe Belastung","id5_desc":"mittlere Belastung"},"content":[{"partregion_name":"Inseln und Marschen","partregion_id":11,"region_name":"Schleswig-Holstein und Hamburg","region_id":10,"Pollen":{"Hasel":{"tomorrow":"0","dayafter_to":"-1","today":"0"},"Esche":{"dayafter_to":"-1","tomorrow":"0","today":"0"},"Ambrosia":{"today":"0","dayafter_to":"-1","tomorrow":"0"},"Birke":{"tomorrow":"0","dayafter_to":"-1","today":"0"},"Beifuss":{"today":"0","tomorrow":"0","dayafter_to":"-1"},"Graeser":{"dayafter_to":"-1","tomorrow":"0","today":"0"},"Erle":{"tomorrow":"0","dayafter_to":"-1","today":"0"},"Roggen":{"today":"0","dayafter_to":"-1","tomorrow":"0"}}},{"partregion_id":12,"partregion_name":"Geest, Schleswig-Holstein und Hamburg","region_id":10,"Pollen":{"Beifuss":{"today":"0","tomorrow":"0","dayafter_to":"-1"},"Graeser":{"today":"0","dayafter_to":"-1","tomorrow":"0"},"Erle":{"tomorrow":"0","dayafter_to":"-1","today":"0"},"Roggen":{"today":"0","tomorrow":"0","dayafter_to":"-1"},"Hasel":{"today":"0","tomorrow":"0","dayafter_to":"-1"},"Esche":{"dayafter_to":"-1","tomorrow":"0","today":"0"},"Ambrosia":{"tomorrow":"0","dayafter_to":"-1","today":"0"},"Birke":{"today":"0","dayafter_to":"-1","tomorrow":"0"}},"region_name":"Schleswig-Holstein und Hamburg"},{"region_name":"Mecklenburg-Vorpommern ","region_id":20,"Pollen":{"Hasel":{"today":"0","dayafter_to":"-1","tomorrow":"0"},"Esche":{"dayafter_to":"-1","tomorrow":"0","today":"0"},"Birke":{"dayafter_to":"-1","tomorrow":"0","today":"0"},"Ambrosia":{"today":"0","dayafter_to":"-1","tomorrow":"0"},"Beifuss":{"dayafter_to":"-1","tomorrow":"0","today":"0"},"Graeser":{"dayafter_to":"-1","tomorrow":"0","today":"0"},"Erle":{"tomorrow":"0","dayafter_to":"-1","today":"0"},"Roggen":{"today":"0","dayafter_to":"-1","tomorrow":"0"}},"partregion_name":"","partregion_id":-1},{"region_name":"Niedersachsen und Bremen","region_id":30,"Pollen":{"Birke":{"dayafter_to":"-1","tomorrow":"0","today":"0"},"Ambrosia":{"today":"0","dayafter_to":"-1","tomorrow":"0"},"Esche":{"tomorrow":"0","dayafter_to":"-1","today":"0"},"Hasel":{"tomorrow":"0","dayafter_to":"-1","today":"0"},"Roggen":{"today":"0","dayafter_to":"-1","tomorrow":"0"},"Erle":{"dayafter_to":"-1","tomorrow":"0","today":"0"},"Graeser":{"today":"0","dayafter_to":"-1","tomorrow":"0"},"Beifuss":{"today":"0","dayafter_to":"-1","tomorrow":"0"}},"partregion_name":"Westl. Niedersachsen/Bremen","partregion_id":31},{"partregion_id":32,"partregion_name":"Östl. Niedersachsen","region_id":30,"Pollen":{"Esche":{"tomorrow":"0","dayafter_to":"-1","today":"0"},"Hasel":{"tomorrow":"0","dayafter_to":"-1","today":"0"},"Birke":{"today":"0","dayafter_to":"-1","tomorrow":"0"},"Ambrosia":{"today":"0","tomorrow":"0","dayafter_to":"-1"},"Graeser":{"dayafter_to":"-1","tomorrow":"0","today":"0"},"Beifuss":{"today":"0","dayafter_to":"-1","tomorrow":"0"},"Roggen":{"today":"0","tomorrow":"0","dayafter_to":"-1"},"Erle":{"today":"0","dayafter_to":"-1","tomorrow":"0"}},"region_name":"Niedersachsen und Bremen"},{"region_name":"Nordrhein-Westfalen","Pollen":{"Graeser":{"today":"0","dayafter_to":"-1","tomorrow":"0"},"Beifuss":{"tomorrow":"0","dayafter_to":"-1","today":"0"},"Roggen":{"today":"0","dayafter_to":"-1","tomorrow":"0"},"Erle":{"today":"0","dayafter_to":"-1","tomorrow":"0"},"Esche":{"dayafter_to":"-1","tomorrow":"0","today":"0"},"Hasel":{"tomorrow":"0","dayafter_to":"-1","today":"0"},"Birke":{"today":"0","tomorrow":"0","dayafter_to":"-1"},"Ambrosia":{"dayafter_to":"-1","tomorrow":"0","today":"0"}},"region_id":40,"partregion_name":"Rhein.-Westfäl. Tiefland","partregion_id":41},{"partregion_name":"Ostwestfalen","partregion_id":42,"region_name":"Nordrhein-Westfalen","region_id":40,"Pollen":{"Hasel":{"today":"0","tomorrow":"0","dayafter_to":"-1"},"Esche":{"today":"0","tomorrow":"0","dayafter_to":"-1"},"Birke":{"tomorrow":"0","dayafter_to":"-1","today":"0"},"Ambrosia":{"tomorrow":"0","dayafter_to":"-1","today":"0"},"Beifuss":{"tomorrow":"0","dayafter_to":"-1","today":"0"},"Graeser":{"dayafter_to":"-1","tomorrow":"0","today":"0"},"Erle":{"today":"0","dayafter_to":"-1","tomorrow":"0"},"Roggen":{"today":"0","dayafter_to":"-1","tomorrow":"0"}}},{"region_name":"Nordrhein-Westfalen","region_id":40,"Pollen":{"Erle":{"today":"0","dayafter_to":"-1","tomorrow":"0"},"Roggen":{"tomorrow":"0","dayafter_to":"-1","today":"0"},"Beifuss":{"dayafter_to":"-1","tomorrow":"0","today":"0"},"Graeser":{"today":"0","tomorrow":"0","dayafter_to":"-1"},"Birke":{"tomorrow":"0","dayafter_to":"-1","today":"0"},"Ambrosia":{"today":"0","dayafter_to":"-1","tomorrow":"0"},"Hasel":{"dayafter_to":"-1","tomorrow":"0","today":"0"},"Esche":{"today":"0","tomorrow":"0","dayafter_to":"-1"}},"partregion_name":"Mittelgebirge NRW","partregion_id":43},{"region_name":"Brandenburg und Berlin ","Pollen":{"Esche":{"tomorrow":"0","dayafter_to":"-1","today":"0"},"Hasel":{"today":"0","tomorrow":"0","dayafter_to":"-1"},"Birke":{"dayafter_to":"-1","tomorrow":"0","today":"0"},"Ambrosia":{"dayafter_to":"-1","tomorrow":"0","today":"0"},"Graeser":{"tomorrow":"0","dayafter_to":"-1","today":"0"},"Beifuss":{"dayafter_to":"-1","tomorrow":"0","today":"0"},"Roggen":{"today":"0","dayafter_to":"-1","tomorrow":"0"},"Erle":{"dayafter_to":"-1","tomorrow":"0","today":"0"}},"region_id":50,"partregion_name":"","partregion_id":-1},{"partregion_id":61,"partregion_name":"Tiefland Sachsen-Anhalt","region_id":60,"Pollen":{"Esche":{"dayafter_to":"-1","tomorrow":"0","today":"0"},"Hasel":{"dayafter_to":"-1","tomorrow":"0","today":"0"},"Ambrosia":{"today":"0","dayafter_to":"-1","tomorrow":"0"},"Birke":{"dayafter_to":"-1","tomorrow":"0","today":"0"},"Graeser":{"tomorrow":"0","dayafter_to":"-1","today":"0"},"Beifuss":{"tomorrow":"0","dayafter_to":"-1","today":"0"},"Roggen":{"dayafter_to":"-1","tomorrow":"0","today":"0"},"Erle":{"dayafter_to":"-1","tomorrow":"0","today":"0"}},"region_name":"Sachsen-Anhalt"},{"partregion_name":"Harz","partregion_id":62,"region_name":"Sachsen-Anhalt","Pollen":{"Esche":{"tomorrow":"0","dayafter_to":"-1","today":"0"},"Hasel":{"tomorrow":"0","dayafter_to":"-1","today":"0"},"Birke":{"today":"0","dayafter_to":"-1","tomorrow":"0"},"Ambrosia":{"today":"0","tomorrow":"0","dayafter_to":"-1"},"Graeser":{"today":"0","dayafter_to":"-1","tomorrow":"0"},"Beifuss":{"today":"0","dayafter_to":"-1","tomorrow":"0"},"Roggen":{"dayafter_to":"-1","tomorrow":"0","today":"0"},"Erle":{"today":"0","tomorrow":"0","dayafter_to":"-1"}},"region_id":60},{"region_name":"Thüringen","region_id":70,"Pollen":{"Beifuss":{"tomorrow":"0","dayafter_to":"-1","today":"0"},"Graeser":{"dayafter_to":"-1","tomorrow":"0","today":"0"},"Erle":{"today":"0","dayafter_to":"-1","tomorrow":"0"},"Roggen":{"tomorrow":"0","dayafter_to":"-1","today":"0"},"Hasel":{"dayafter_to":"-1","tomorrow":"0","today":"0"},"Esche":{"dayafter_to":"-1","tomorrow":"0","today":"0"},"Birke":{"tomorrow":"0","dayafter_to":"-1","today":"0"},"Ambrosia":{"tomorrow":"0","dayafter_to":"-1","today":"0"}},"partregion_name":"Tiefland Thüringen","partregion_id":71},{"region_name":"Thüringen","region_id":70,"Pollen":{"Roggen":{"dayafter_to":"-1","tomorrow":"0","today":"0"},"Erle":{"tomorrow":"0","dayafter_to":"-1","today":"0"},"Graeser":{"today":"0","dayafter_to":"-1","tomorrow":"0"},"Beifuss":{"dayafter_to":"-1","tomorrow":"0","today":"0"},"Ambrosia":{"dayafter_to":"-1","tomorrow":"0","today":"0"},"Birke":{"dayafter_to":"-1","tomorrow":"0","today":"0"},"Esche":{"today":"0","tomorrow":"0","dayafter_to":"-1"},"Hasel":{"tomorrow":"0","dayafter_to":"-1","today":"0"}},"partregion_name":"Mittelgebirge Thüringen","partregion_id":72},{"partregion_id":81,"partregion_name":"Tiefland Sachsen","Pollen":{"Erle":{"dayafter_to":"-1","tomorrow":"0","today":"0"},"Roggen":{"tomorrow":"0","dayafter_to":"-1","today":"0"},"Beifuss":{"dayafter_to":"-1","tomorrow":"0","today":"0"},"Graeser":{"tomorrow":"0","dayafter_to":"-1","today":"0"},"Ambrosia":{"today":"0","dayafter_to":"-1","tomorrow":"0"},"Birke":{"today":"0","dayafter_to":"-1","tomorrow":"0"},"Hasel":{"today":"0","tomorrow":"0","dayafter_to":"-1"},"Esche":{"today":"0","tomorrow":"0","dayafter_to":"-1"}},"region_id":80,"region_name":"Sachsen"},{"partregion_name":"Mittelgebirge Sachsen","partregion_id":82,"region_name":"Sachsen","region_id":80,"Pollen":{"Hasel":{"today":"0","tomorrow":"0","dayafter_to":"-1"},"Esche":{"dayafter_to":"-1","tomorrow":"0","today":"0"},"Ambrosia":{"dayafter_to":"-1","tomorrow":"0","today":"0"},"Birke":{"dayafter_to":"-1","tomorrow":"0","today":"0"},"Beifuss":{"dayafter_to":"-1","tomorrow":"0","today":"0"},"Graeser":{"dayafter_to":"-1","tomorrow":"0","today":"0"},"Erle":{"tomorrow":"0","dayafter_to":"-1","today":"0"},"Roggen":{"today":"0","tomorrow":"0","dayafter_to":"-1"}}},{"partregion_id":91,"partregion_name":"Nordhessen und hess. Mittelgebirge","region_id":90,"Pollen":{"Roggen":{"today":"0","tomorrow":"0","dayafter_to":"-1"},"Erle":{"tomorrow":"0","dayafter_to":"-1","today":"0"},"Graeser":{"tomorrow":"0","dayafter_to":"-1","today":"0"},"Beifuss":{"dayafter_to":"-1","tomorrow":"0","today":"0"},"Birke":{"dayafter_to":"-1","tomorrow":"0","today":"0"},"Ambrosia":{"today":"0","dayafter_to":"-1","tomorrow":"0"},"Esche":{"today":"0","dayafter_to":"-1","tomorrow":"0"},"Hasel":{"tomorrow":"0","dayafter_to":"-1","today":"0"}},"region_name":"Hessen"},{"Pollen":{"Hasel":{"tomorrow":"0","dayafter_to":"-1","today":"0"},"Esche":{"dayafter_to":"-1","tomorrow":"0","today":"0"},"Ambrosia":{"dayafter_to":"-1","tomorrow":"0","today":"0"},"Birke":{"today":"0","tomorrow":"0","dayafter_to":"-1"},"Beifuss":{"today":"0","tomorrow":"0","dayafter_to":"-1"},"Graeser":{"dayafter_to":"-1","tomorrow":"0","today":"0"},"Erle":{"tomorrow":"0","dayafter_to":"-1","today":"0"},"Roggen":{"dayafter_to":"-1","tomorrow":"0","today":"0"}},"region_id":90,"region_name":"Hessen","partregion_id":92,"partregion_name":"Rhein-Main"},{"partregion_name":"Saarland","partregion_id":103,"region_name":"Rheinland-Pfalz und Saarland","region_id":100,"Pollen":{"Birke":{"today":"0","tomorrow":"0","dayafter_to":"-1"},"Ambrosia":{"dayafter_to":"-1","tomorrow":"0","today":"0"},"Esche":{"tomorrow":"0","dayafter_to":"-1","today":"0"},"Hasel":{"today":"0","dayafter_to":"-1","tomorrow":"0"},"Roggen":{"tomorrow":"0","dayafter_to":"-1","today":"0"},"Erle":{"dayafter_to":"-1","tomorrow":"0","today":"0"},"Graeser":{"today":"0","tomorrow":"0","dayafter_to":"-1"},"Beifuss":{"dayafter_to":"-1","tomorrow":"0","today":"0"}}},{"partregion_id":101,"partregion_name":"Rhein, Pfalz, Nahe und Mosel","Pollen":{"Birke":{"today":"0","tomorrow":"0","dayafter_to":"-1"},"Ambrosia":{"tomorrow":"0","dayafter_to":"-1","today":"0"},"Esche":{"dayafter_to":"-1","tomorrow":"0","today":"0"},"Hasel":{"tomorrow":"0","dayafter_to":"-1","today":"0"},"Roggen":{"today":"0","tomorrow":"0","dayafter_to":"-1"},"Erle":{"tomorrow":"0","dayafter_to":"-1","today":"0"},"Graeser":{"today":"0","dayafter_to":"-1","tomorrow":"0"},"Beifuss":{"today":"0","dayafter_to":"-1","tomorrow":"0"}},"region_id":100,"region_name":"Rheinland-Pfalz und Saarland"},{"region_id":100,"Pollen":{"Esche":{"tomorrow":"0","dayafter_to":"-1","today":"0"},"Hasel":{"dayafter_to":"-1","tomorrow":"0","today":"0"},"Ambrosia":{"tomorrow":"0","dayafter_to":"-1","today":"0"},"Birke":{"dayafter_to":"-1","tomorrow":"0","today":"0"},"Graeser":{"dayafter_to":"-1","tomorrow":"0","today":"0"},"Beifuss":{"today":"0","tomorrow":"0","dayafter_to":"-1"},"Roggen":{"today":"0","tomorrow":"0","dayafter_to":"-1"},"Erle":{"tomorrow":"0","dayafter_to":"-1","today":"0"}},"region_name":"Rheinland-Pfalz und Saarland","partregion_id":102,"partregion_name":"Mittelgebirgsbereich Rheinland-Pfalz"},{"region_name":"Baden-Württemberg","Pollen":{"Esche":{"dayafter_to":"-1","tomorrow":"0","today":"0"},"Hasel":{"today":"0","dayafter_to":"-1","tomorrow":"0"},"Ambrosia":{"tomorrow":"0","dayafter_to":"-1","today":"0"},"Birke":{"today":"0","dayafter_to":"-1","tomorrow":"0"},"Graeser":{"dayafter_to":"-1","tomorrow":"0","today":"0"},"Beifuss":{"today":"0","dayafter_to":"-1","tomorrow":"0"},"Roggen":{"tomorrow":"0","dayafter_to":"-1","today":"0"},"Erle":{"today":"0","dayafter_to":"-1","tomorrow":"0"}},"region_id":110,"partregion_name":"Oberrhein und unteres Neckartal","partregion_id":111},{"region_id":110,"Pollen":{"Esche":{"tomorrow":"0","dayafter_to":"-1","today":"0"},"Hasel":{"dayafter_to":"-1","tomorrow":"0","today":"0"},"Birke":{"today":"0","dayafter_to":"-1","tomorrow":"0"},"Ambrosia":{"today":"0","dayafter_to":"-1","tomorrow":"0"},"Graeser":{"tomorrow":"0","dayafter_to":"-1","today":"0"},"Beifuss":{"today":"0","tomorrow":"0","dayafter_to":"-1"},"Roggen":{"today":"0","tomorrow":"0","dayafter_to":"-1"},"Erle":{"tomorrow":"0","dayafter_to":"-1","today":"0"}},"region_name":"Baden-Württemberg","partregion_id":112,"partregion_name":"Hohenlohe/mittlerer Neckar/Oberschwaben"},{"Pollen":{"Graeser":{"today":"0","dayafter_to":"-1","tomorrow":"0"},"Beifuss":{"today":"0","dayafter_to":"-1","tomorrow":"0"},"Roggen":{"dayafter_to":"-1","tomorrow":"0","today":"0"},"Erle":{"tomorrow":"0","dayafter_to":"-1","today":"0"},"Esche":{"today":"0","tomorrow":"0","dayafter_to":"-1"},"Hasel":{"dayafter_to":"-1","tomorrow":"0","today":"0"},"Birke":{"dayafter_to":"-1","tomorrow":"0","today":"0"},"Ambrosia":{"today":"0","tomorrow":"0","dayafter_to":"-1"}},"region_id":110,"region_name":"Baden-Württemberg","partregion_id":113,"partregion_name":"Mittelgebirge Baden-Württemberg"},{"region_name":"Bayern","Pollen":{"Roggen":{"tomorrow":"0","dayafter_to":"-1","today":"0"},"Erle":{"today":"0","tomorrow":"0","dayafter_to":"-1"},"Graeser":{"today":"0","tomorrow":"0","dayafter_to":"-1"},"Beifuss":{"today":"0","tomorrow":"0","dayafter_to":"-1"},"Birke":{"today":"0","tomorrow":"0","dayafter_to":"-1"},"Ambrosia":{"today":"0","tomorrow":"0","dayafter_to":"-1"},"Esche":{"tomorrow":"0","dayafter_to":"-1","today":"0"},"Hasel":{"today":"0","tomorrow":"0","dayafter_to":"-1"}},"region_id":120,"partregion_name":"Allgäu/Oberbayern/Bay. Wald","partregion_id":121},{"partregion_id":122,"partregion_name":"Donauniederungen","Pollen":{"Roggen":{"tomorrow":"0","dayafter_to":"-1","today":"0"},"Erle":{"tomorrow":"0","dayafter_to":"-1","today":"0"},"Graeser":{"today":"0","tomorrow":"0","dayafter_to":"-1"},"Beifuss":{"dayafter_to":"-1","tomorrow":"0","today":"0"},"Birke":{"dayafter_to":"-1","tomorrow":"0","today":"0"},"Ambrosia":{"dayafter_to":"-1","tomorrow":"0","today":"0"},"Esche":{"today":"0","tomorrow":"0","dayafter_to":"-1"},"Hasel":{"tomorrow":"0","dayafter_to":"-1","today":"0"}},"region_id":120,"region_name":"Bayern"},{"Pollen":{"Beifuss":{"dayafter_to":"-1","tomorrow":"0","today":"0"},"Graeser":{"today":"0","tomorrow":"0","dayafter_to":"-1"},"Erle":{"tomorrow":"0","dayafter_to":"-1","today":"0"},"Roggen":{"dayafter_to":"-1","tomorrow":"0","today":"0"},"Hasel":{"dayafter_to":"-1","tomorrow":"0","today":"0"},"Esche":{"today":"0","dayafter_to":"-1","tomorrow":"0"},"Birke":{"today":"0","dayafter_to":"-1","tomorrow":"0"},"Ambrosia":{"today":"0","tomorrow":"0","dayafter_to":"-1"}},"region_id":120,"region_name":"Bayern","partregion_id":123,"partregion_name":"Bayern n. der Donau, o. Bayr. Wald, o. Mainfranken"},{"region_name":"Bayern","Pollen":{"Erle":{"dayafter_to":"-1","tomorrow":"0","today":"0"},"Roggen":{"tomorrow":"0","dayafter_to":"-1","today":"0"},"Beifuss":{"today":"0","tomorrow":"0","dayafter_to":"-1"},"Graeser":{"today":"0","dayafter_to":"-1","tomorrow":"0"},"Ambrosia":{"today":"0","tomorrow":"0","dayafter_to":"-1"},"Birke":{"tomorrow":"0","dayafter_to":"-1","today":"0"},"Hasel":{"dayafter_to":"-1","tomorrow":"0","today":"0"},"Esche":{"today":"0","dayafter_to":"-1","tomorrow":"0"}},"region_id":120,"partregion_name":"Mainfranken","partregion_id":124}],"sender":"Deutscher Wetterdienst - Medizin-Meteorologie","name":"Pollenflug-Gefahrenindex für Deutschland ausgegeben vom Deutschen Wetterdienst","next_update":"2020-11-19 11:00 Uhr","last_update":"2020-11-18 11:00 Uhr"}